pyaiagent/__init__.py
pyaiagent/py.typed
pyaiagent/openai/__init__.py
pyaiagent/openai/agent.py
pyaiagent/openai/client.py
pyaiagent/openai/config.py
pyaiagent/openai/shutdown.py
pyaiagent/openai/exceptions/__init__.py
pyaiagent/openai/exceptions/definition.py
pyaiagent/openai/exceptions/process.py
pyaiagent/openai/manager/__init__.py
pyaiagent/openai/manager/config.py
pyaiagent/openai/manager/instruction.py
pyaiagent/openai/manager/tool.py
pyaiagent/openai/manager/tool_schema.py
pyaiagent/utils/__init__.py
pyaiagent/utils/singleton.py
pyaiagent-0.1.4.dist-info/licenses/LICENSE
pyaiagent-0.1.4.dist-info/METADATA
pyaiagent-0.1.4.dist-info/WHEEL
pyaiagent-0.1.4.dist-info/top_level.txt
pyaiagent-0.1.4.dist-info/RECORD
