Metadata-Version: 2.4
Name: pyaiagent
Version: 0.1.4
Summary: PyAiAgent is a modern, fast (high-performance), async framework for building AI agents with pythonic code.
Author-email: Troy M Jose <troymjose@gmail.com>
License: MIT
Project-URL: Homepage, https://github.com/troymjose/pyaiagent
Project-URL: Repository, https://github.com/troymjose/pyaiagent
Project-URL: Issues, https://github.com/troymjose/pyaiagent/issues
Keywords: openai,ai,agent,llm,gpt,async,framework
Classifier: Development Status :: 4 - Beta
Classifier: Intended Audience :: Developers
Classifier: License :: OSI Approved :: MIT License
Classifier: Operating System :: OS Independent
Classifier: Programming Language :: Python :: 3
Classifier: Programming Language :: Python :: 3.10
Classifier: Programming Language :: Python :: 3.11
Classifier: Programming Language :: Python :: 3.12
Classifier: Programming Language :: Python :: 3.13
Classifier: Topic :: Scientific/Engineering :: Artificial Intelligence
Classifier: Typing :: Typed
Classifier: Framework :: AsyncIO
Requires-Python: >=3.10
License-File: LICENSE
Requires-Dist: openai>=1.0.0
Requires-Dist: orjson>=3.9.0
Provides-Extra: dev
Requires-Dist: pytest>=7.0.0; extra == "dev"
Requires-Dist: pytest-asyncio>=0.21.0; extra == "dev"
Dynamic: license-file
